{
  "lastSync": 1748353408789,
  "blobFiles": {
    "hero_images/LBP Hero-1.jpg": {
      "driveId": "10Pzn835ffJirRE2grg7jhE4OLF6gXd4-",
      "pathname": "hero_images/LBP Hero-1.jpg"
    },
    "hero_images/LBP Hero-9.jpg": {
      "driveId": "16-Fb_HBZBrdHA1e_HVtGYnik1QkQsK-b",
      "pathname": "hero_images/LBP Hero-9.jpg"
    },
    "hero_images/LBP Hero-8.jpg": {
      "driveId": "1LCaZpJA4E8KStxmJDuyT6QRl79vKLrHb",
      "pathname": "hero_images/LBP Hero-8.jpg"
    },
    "hero_images/LBP Hero-7.jpg": {
      "driveId": "1aasKl2Qn31ZDE_b3q2E89OukAQ3Ij31y",
      "pathname": "hero_images/LBP Hero-7.jpg"
    },
    "hero_images/LBP Hero-4.jpg": {
      "driveId": "1m9SC539BkPSvc6wxqiZ0e63SXA_bSndm",
      "pathname": "hero_images/LBP Hero-4.jpg"
    },
    "hero_images/LBP Hero-6.jpg": {
      "driveId": "1IH_pFr5XqNGYbf6uIS58hQOqRYYYoLCP",
      "pathname": "hero_images/LBP Hero-6.jpg"
    },
    "hero_images/LBP Hero-3.jpg": {
      "driveId": "1Csu036qJjaJjEKcsAPJK-oV6ER7MT0jp",
      "pathname": "hero_images/LBP Hero-3.jpg"
    },
    "hero_images/LBP Hero-5.jpg": {
      "driveId": "1JhSxoAX7pEnWmB-LWcY4kQTLeCisNsIc",
      "pathname": "hero_images/LBP Hero-5.jpg"
    },
    "hero_images/LBP Hero-2.jpg": {
      "driveId": "14RNUSvyosUSI_6aGC1B-jM0chOweYU5V",
      "pathname": "hero_images/LBP Hero-2.jpg"
    }
  }
}